raceplotly/__init__.py
raceplotly/plots.py
raceplotly-0.1.7.dist-info/LICENSE
raceplotly-0.1.7.dist-info/METADATA
raceplotly-0.1.7.dist-info/WHEEL
raceplotly-0.1.7.dist-info/top_level.txt
raceplotly-0.1.7.dist-info/RECORD
