Metadata-Version: 2.1
Name: raceplotly
Version: 0.1.7
Summary: Tiny package to make 'race' barplots using plotly
Home-page: https://github.com/lc5415/raceplotly
Author: Luis Chaves
Author-email: lc5415@ic.ac.uk
License: UNKNOWN
Platform: UNKNOWN
Classifier: Programming Language :: Python :: 3
Classifier: License :: OSI Approved :: MIT License
Classifier: Operating System :: OS Independent
Requires-Python: >=3.7
Requires-Dist: pandas
Requires-Dist: numpy
Requires-Dist: plotly
